[
  {
    "arguments": [
      "/usr/lib/llvm-11/bin/clang",
      "-std=c++17",
      "-pedantic",
      "-O3",
      "-fno-exceptions",
      "-flto",
      "-fno-permissive",
      "-DNDEBUG",
      "-DFF_BOUNDED_BUFFER",
      "-DDEFAULT_BUFFER_CAPACITY=32786",
      "-fno-lto",
      "-Og",
      "-g",
      "-fno-inline",
      "-Wall",
      "-Wextra",
      "-UNDEBUG",
      "-Wpedantic",
      "-I/home/cosimone/.local/include",
      "-I/home/cosimone/.local/include/gsl",
      "-I/home/cosimone/fastflow",
      "-I/home/cosimone/.local/include/wf",
      "-c",
      "example1.cpp",
      "-o",
      "example1.o"
    ],
    "directory": "/home/cosimone/workspaces/windflow-examples",
    "file": "/home/cosimone/workspaces/windflow-examples/example1.cpp",
    "output": "/home/cosimone/workspaces/windflow-examples/example1.o"
  },
  {
    "arguments": [
      "/usr/lib/llvm-11/bin/clang",
      "-std=c++17",
      "-pedantic",
      "-O3",
      "-fno-exceptions",
      "-flto",
      "-fno-permissive",
      "-DNDEBUG",
      "-DFF_BOUNDED_BUFFER",
      "-DDEFAULT_BUFFER_CAPACITY=32786",
      "-fno-lto",
      "-Og",
      "-g",
      "-fno-inline",
      "-Wall",
      "-Wextra",
      "-UNDEBUG",
      "-Wpedantic",
      "-I/home/cosimone/.local/include",
      "-I/home/cosimone/.local/include/gsl",
      "-I/home/cosimone/fastflow",
      "-I/home/cosimone/.local/include/wf",
      "-c",
      "mo-machine-outlier/mo.cpp",
      "-o",
      "mo-machine-outlier/mo.o"
    ],
    "directory": "/home/cosimone/workspaces/windflow-examples",
    "file": "/home/cosimone/workspaces/windflow-examples/mo-machine-outlier/mo.cpp",
    "output": "/home/cosimone/workspaces/windflow-examples/mo-machine-outlier/mo.o"
  },
  {
    "arguments": [
      "/usr/lib/llvm-11/bin/clang",
      "-std=c++17",
      "-pedantic",
      "-O3",
      "-fno-exceptions",
      "-flto",
      "-fno-permissive",
      "-DNDEBUG",
      "-DFF_BOUNDED_BUFFER",
      "-DDEFAULT_BUFFER_CAPACITY=32786",
      "-fno-lto",
      "-Og",
      "-g",
      "-fno-inline",
      "-Wall",
      "-Wextra",
      "-UNDEBUG",
      "-Wpedantic",
      "-I/home/cosimone/.local/include",
      "-I/home/cosimone/.local/include/gsl",
      "-I/home/cosimone/fastflow",
      "-I/home/cosimone/.local/include/wf",
      "-c",
      "rl-reinforcement-learner/rl.cpp",
      "-o",
      "rl-reinforcement-learner/rl.o"
    ],
    "directory": "/home/cosimone/workspaces/windflow-examples",
    "file": "/home/cosimone/workspaces/windflow-examples/rl-reinforcement-learner/rl.cpp",
    "output": "/home/cosimone/workspaces/windflow-examples/rl-reinforcement-learner/rl.o"
  },
  {
    "arguments": [
      "/usr/lib/llvm-11/bin/clang",
      "-std=c++17",
      "-pedantic",
      "-O3",
      "-fno-exceptions",
      "-flto",
      "-fno-permissive",
      "-DNDEBUG",
      "-DFF_BOUNDED_BUFFER",
      "-DDEFAULT_BUFFER_CAPACITY=32786",
      "-fno-lto",
      "-Og",
      "-g",
      "-fno-inline",
      "-Wall",
      "-Wextra",
      "-UNDEBUG",
      "-Wpedantic",
      "-I/home/cosimone/.local/include",
      "-I/home/cosimone/.local/include/gsl",
      "-I/home/cosimone/fastflow",
      "-I/home/cosimone/.local/include/wf",
      "-c",
      "sa-sentiment-analysis/sa.cpp",
      "-o",
      "sa-sentiment-analysis/sa.o"
    ],
    "directory": "/home/cosimone/workspaces/windflow-examples",
    "file": "/home/cosimone/workspaces/windflow-examples/sa-sentiment-analysis/sa.cpp",
    "output": "/home/cosimone/workspaces/windflow-examples/sa-sentiment-analysis/sa.o"
  },
  {
    "arguments": [
      "/usr/lib/llvm-11/bin/clang",
      "-std=c++17",
      "-pedantic",
      "-O3",
      "-fno-exceptions",
      "-flto",
      "-fno-permissive",
      "-DNDEBUG",
      "-DFF_BOUNDED_BUFFER",
      "-DDEFAULT_BUFFER_CAPACITY=32786",
      "-fno-lto",
      "-Og",
      "-g",
      "-fno-inline",
      "-Wall",
      "-Wextra",
      "-UNDEBUG",
      "-Wpedantic",
      "-I/home/cosimone/.local/include",
      "-I/home/cosimone/.local/include/gsl",
      "-I/home/cosimone/fastflow",
      "-I/home/cosimone/.local/include/wf",
      "-c",
      "tt-trending-topics/tt.cpp",
      "-o",
      "tt-trending-topics/tt.o"
    ],
    "directory": "/home/cosimone/workspaces/windflow-examples",
    "file": "/home/cosimone/workspaces/windflow-examples/tt-trending-topics/tt.cpp",
    "output": "/home/cosimone/workspaces/windflow-examples/tt-trending-topics/tt.o"
  },
  {
    "arguments": [
      "/usr/lib/llvm-11/bin/clang",
      "-std=c++17",
      "-pedantic",
      "-O3",
      "-fno-exceptions",
      "-flto",
      "-fno-permissive",
      "-DNDEBUG",
      "-DFF_BOUNDED_BUFFER",
      "-DDEFAULT_BUFFER_CAPACITY=32786",
      "-fno-lto",
      "-Og",
      "-g",
      "-fno-inline",
      "-Wall",
      "-Wextra",
      "-UNDEBUG",
      "-Wpedantic",
      "-I/home/cosimone/.local/include",
      "-I/home/cosimone/.local/include/gsl",
      "-I/home/cosimone/fastflow",
      "-I/home/cosimone/.local/include/wf",
      "-c",
      "example2.cpp",
      "-o",
      "example2.o"
    ],
    "directory": "/home/cosimone/workspaces/windflow-examples",
    "file": "/home/cosimone/workspaces/windflow-examples/example2.cpp",
    "output": "/home/cosimone/workspaces/windflow-examples/example2.o"
  }
]
